LICENSE.txt
MANIFEST.in
README.md
setup.py
test/test.py
tk_r_em/__init__.py
tk_r_em/tk_r_em.py
tk_r_em/version.py
tk_r_em.egg-info/PKG-INFO
tk_r_em.egg-info/SOURCES.txt
tk_r_em.egg-info/dependency_links.txt
tk_r_em.egg-info/requires.txt
tk_r_em.egg-info/top_level.txt
tk_r_em/models/sfr_hrsem/fingerprint.pb
tk_r_em/models/sfr_hrsem/keras_metadata.pb
tk_r_em/models/sfr_hrsem/saved_model.pb
tk_r_em/models/sfr_hrsem/variables/variables.data-00000-of-00001
tk_r_em/models/sfr_hrsem/variables/variables.index
tk_r_em/models/sfr_hrstem/fingerprint.pb
tk_r_em/models/sfr_hrstem/keras_metadata.pb
tk_r_em/models/sfr_hrstem/saved_model.pb
tk_r_em/models/sfr_hrstem/variables/variables.data-00000-of-00001
tk_r_em/models/sfr_hrstem/variables/variables.index
tk_r_em/models/sfr_hrtem/fingerprint.pb
tk_r_em/models/sfr_hrtem/keras_metadata.pb
tk_r_em/models/sfr_hrtem/saved_model.pb
tk_r_em/models/sfr_hrtem/variables/variables.data-00000-of-00001
tk_r_em/models/sfr_hrtem/variables/variables.index
tk_r_em/models/sfr_lrsem/fingerprint.pb
tk_r_em/models/sfr_lrsem/keras_metadata.pb
tk_r_em/models/sfr_lrsem/saved_model.pb
tk_r_em/models/sfr_lrsem/variables/variables.data-00000-of-00001
tk_r_em/models/sfr_lrsem/variables/variables.index
tk_r_em/models/sfr_lrstem/fingerprint.pb
tk_r_em/models/sfr_lrstem/keras_metadata.pb
tk_r_em/models/sfr_lrstem/saved_model.pb
tk_r_em/models/sfr_lrstem/variables/variables.data-00000-of-00001
tk_r_em/models/sfr_lrstem/variables/variables.index
tk_r_em/models/sfr_lrtem/fingerprint.pb
tk_r_em/models/sfr_lrtem/keras_metadata.pb
tk_r_em/models/sfr_lrtem/saved_model.pb
tk_r_em/models/sfr_lrtem/variables/variables.data-00000-of-00001
tk_r_em/models/sfr_lrtem/variables/variables.index
tk_r_em/test_data/exp_hrstem.h5
tk_r_em/test_data/sfr_hrsem.h5
tk_r_em/test_data/sfr_hrstem.h5
tk_r_em/test_data/sfr_hrtem.h5
tk_r_em/test_data/sfr_lrsem.h5
tk_r_em/test_data/sfr_lrstem.h5
tk_r_em/test_data/sfr_lrtem.h5
tk_r_em/test_data/sgl_exp_hrstem.h5