Metadata-Version: 2.1
Name: tk-r-em
Version: 1.0.4
Summary: Deep convolutional neural networks to restore single-shot electron microscopy images
Home-page: https://github.com/Ivanlh20/r_em/
Author: Ivan Lobato
Author-email: ivanlh20@gmail.com
License: GPLv3
Project-URL: Repository, https://github.com/Ivanlh20/r_em/
Classifier: Development Status :: 5 - Production/Stable
Classifier: Intended Audience :: Science/Research
Classifier: Topic :: Scientific/Engineering
Classifier: License :: OSI Approved :: GNU General Public License v3 (GPLv3)
Classifier: Operating System :: POSIX :: Linux
Classifier: Programming Language :: Python :: 3.7
Classifier: Programming Language :: Python :: 3.8
Classifier: Programming Language :: Python :: 3.9
Classifier: Programming Language :: Python :: 3.10
License-File: LICENSE.txt
